pyifcount/__init__.py
pyifcount/cli.py
pyifcount-0.0.4.dist-info/entry_points.txt
pyifcount-0.0.4.dist-info/LICENSE
pyifcount-0.0.4.dist-info/WHEEL
pyifcount-0.0.4.dist-info/METADATA
pyifcount-0.0.4.dist-info/RECORD
